clutui/__init__.py
clutui/main.py
clutui/settings.json
clutui/assets/icons/change.png
clutui/assets/icons/close2.png
clutui/assets/icons/done.png
clutui/assets/icons/f5.png
clutui/assets/icons/image.png
clutui/assets/icons/list.png
clutui/assets/icons/logo.png
clutui/assets/icons/max.png
clutui/assets/icons/max3.png
clutui/assets/icons/mini.png
clutui/assets/icons/off.png
clutui/assets/icons/play.png
clutui/assets/icons/reply.png
clutui/assets/icons/restore.png
clutui/assets/icons/search.png
clutui/assets/icons/send.png
clutui/assets/icons/share.png
clutui/assets/icons/shoucang.png
clutui/assets/icons/tips.png
clutui/assets/icons/pages_icon/about.png
clutui/assets/icons/pages_icon/compass.png
clutui/assets/icons/pages_icon/home.png
clutui/assets/icons/pages_icon/images.png
clutui/assets/icons/pages_icon/info.png
clutui/assets/icons/pages_icon/settings.png
clutui/assets/icons/pages_icon/share.png
clutui/assets/icons/pages_icon/stars.png
clutui/assets/icons/pages_icon/writes.png
clutui/assets/pages/about.py
clutui/assets/pages/home.py
clutui/assets/styles/sidebar.qss
clutui/assets/styles/sidebar_expanded.qss
clutui/assets/ui/content.qss
clutui/assets/ui/pf_title_bar.qss
clutui/assets/ui/sidebar.qss
clutui/assets/ui/sidebar_expanded.qss
clutui/assets/utils/clut_button.py
clutui/assets/utils/clut_card.py
clutui/assets/utils/clut_image_card.py
clutui/assets/utils/main_ui.py
clutui/assets/utils/message_box.py
clutui/assets/utils/notification_manager.py
clutui/assets/utils/overlay_notification.py
clutui/assets/utils/page_manager.py
clutui/assets/utils/settings_manager.py
clutui/assets/utils/style_loader.py
clutui/assets/utils/titlebar.py
clutui-1.0.1.5600.dist-info/LICENSE
clutui-1.0.1.5600.dist-info/METADATA
clutui-1.0.1.5600.dist-info/WHEEL
clutui-1.0.1.5600.dist-info/top_level.txt
clutui-1.0.1.5600.dist-info/RECORD
