Metadata-Version: 2.1
Name: clutui
Version: 1.0.1.5600
Summary: 一个现代化的PyQt5 UI框架
Home-page: https://github.com/你的用户名/clutui
Author: 你的名字
Author-email: ZZBuAoYe <zzbuaoye@gmail.com>
Project-URL: Homepage, https://github.com/buaoyezz/PyQt-ClutUI
Project-URL: Bug Tracker, https://github.com/buaoyezz/PyQt-ClutUI/issues
Classifier: Programming Language :: Python :: 3
Classifier: License :: OSI Approved :: MIT License
Classifier: Operating System :: OS Independent
Requires-Python: >=3.9
License-File: LICENSE
Requires-Dist: PyQt5>=5.15.0
